quiz_cultura/__init__.py
quiz_cultura/main.py
quiz_cultura_general-1.0.0.dist-info/licenses/LICENSE
quiz_cultura_general-1.0.0.dist-info/METADATA
quiz_cultura_general-1.0.0.dist-info/WHEEL
quiz_cultura_general-1.0.0.dist-info/entry_points.txt
quiz_cultura_general-1.0.0.dist-info/top_level.txt
quiz_cultura_general-1.0.0.dist-info/RECORD
