Metadata-Version: 2.4
Name: quiz-cultura-general
Version: 1.0.0
Summary: Quiz interactivo de cultura general
Author: Patricia Elena Paun
License: MIT
Requires-Python: >=3.6
License-File: LICENSE
Dynamic: license-file
